diffpy/__init__.py
diffpy/srxplanargui/__init__.py
diffpy/srxplanargui/calibration.py
diffpy/srxplanargui/datacontainer.py
diffpy/srxplanargui/gitarchive.cfg
diffpy/srxplanargui/help.py
diffpy/srxplanargui/imageplot.py
diffpy/srxplanargui/live.py
diffpy/srxplanargui/selectfiles.py
diffpy/srxplanargui/srxconfig.py
diffpy/srxplanargui/srxgui.py
diffpy/srxplanargui/srxguiapp.py
diffpy/srxplanargui/srxplanargui_app.py
diffpy/srxplanargui/version.py
diffpy/srxplanargui/images/01.png
diffpy/srxplanargui/images/02.png
diffpy/srxplanargui/images/03.png
diffpy/srxplanargui/images/04.png
diffpy/srxplanargui/images/05.png
diffpy/srxplanargui/images/06.png
diffpy/srxplanargui/images/07.png
diffpy/srxplanargui/images/08.png
diffpy/srxplanargui/images/09.png
diffpy/srxplanargui/images/10.png
diffpy/srxplanargui/images/11.png
diffpy/srxplanargui/images/12.png
diffpy/srxplanargui/images/13.png
diffpy/srxplanargui/images/14.png
diffpy/srxplanargui/images/15.png
diffpy/srxplanargui/images/16.png
diffpy/srxplanargui/images/17.png
diffpy/srxplanargui/images/18.png
diffpy/srxplanargui/images/19.png
diffpy/srxplanargui/images/20.png
diffpy/srxplanargui/images/21.png
diffpy/srxplanargui/images/22.png
diffpy/srxplanargui/images/gitarchive.cfg
diffpy/srxplanargui/images/icon.ico
diffpy/srxplanargui/images/icon.png
diffpy_srxplanargui-1.0.0rc2.dist-info/licenses/AUTHORS.rst
diffpy_srxplanargui-1.0.0rc2.dist-info/licenses/LICENSE.rst
diffpy_srxplanargui-1.0.0rc2.dist-info/METADATA
diffpy_srxplanargui-1.0.0rc2.dist-info/WHEEL
diffpy_srxplanargui-1.0.0rc2.dist-info/entry_points.txt
diffpy_srxplanargui-1.0.0rc2.dist-info/top_level.txt
diffpy_srxplanargui-1.0.0rc2.dist-info/RECORD
