Metadata-Version: 2.4
Name: diffpy.srxplanargui
Version: 1.0.0rc2
Summary: xPDFsuite, a software for PDF transformation and visualization.
Author-email: Simon Billinge <sb2896@columbia.edu>
Maintainer-email: Simon Billinge <sb2896@columbia.edu>
Project-URL: Homepage, https://github.com/diffpy/diffpy.srxplanargui/
Project-URL: Issues, https://github.com/diffpy/diffpy.srxplanargui/issues/
Keywords: diffpy,pdf,data interpretation
Classifier: Development Status :: 5 - Production/Stable
Classifier: Environment :: Console
Classifier: Intended Audience :: Developers
Classifier: Intended Audience :: Science/Research
Classifier: License :: OSI Approved :: BSD License
Classifier: Operating System :: MacOS :: MacOS X
Classifier: Operating System :: Microsoft :: Windows
Classifier: Operating System :: POSIX
Classifier: Operating System :: Unix
Classifier: Programming Language :: Python :: 3.11
Classifier: Programming Language :: Python :: 3.12
Classifier: Programming Language :: Python :: 3.13
Classifier: Topic :: Scientific/Engineering :: Physics
Classifier: Topic :: Scientific/Engineering :: Chemistry
Requires-Python: <3.14,>=3.11
License-File: LICENSE.rst
License-File: AUTHORS.rst
Requires-Dist: numpy
Requires-Dist: chaco
Requires-Dist: pyface
Requires-Dist: scipy
Requires-Dist: traits
Requires-Dist: traitsui
Requires-Dist: fabio
Requires-Dist: pyfai
Requires-Dist: matplotlib
Requires-Dist: diffpy.srxplanar
Dynamic: license-file
